LICENSE.txt
MANIFEST.in
README.rst
requirements-test.txt
setup.py
jsonrpc_async/__init__.py
jsonrpc_async/jsonrpc.py
jsonrpc_async.egg-info/PKG-INFO
jsonrpc_async.egg-info/SOURCES.txt
jsonrpc_async.egg-info/dependency_links.txt
jsonrpc_async.egg-info/requires.txt
jsonrpc_async.egg-info/top_level.txt